clickhouse/__init__.py
clickhouse/database.py
clickhouse/engines.py
clickhouse/fields.py
clickhouse/models.py
clickhouse/utils.py
clickhouse-0.1.6.dist-info/DESCRIPTION.rst
clickhouse-0.1.6.dist-info/METADATA
clickhouse-0.1.6.dist-info/RECORD
clickhouse-0.1.6.dist-info/WHEEL
clickhouse-0.1.6.dist-info/metadata.json
clickhouse-0.1.6.dist-info/top_level.txt
