Metadata-Version: 2.0
Name: clickhouse
Version: 0.1.6
Summary: A Python library for working with the ClickHouse database
Home-page: https://bitbucket.com/ppodolsky/clickhouse-python
Author: ppodolsky
Author-email: ppodolsky@yandex-team.ru
License: UNKNOWN
Platform: UNKNOWN
Classifier: Intended Audience :: Developers
Classifier: Intended Audience :: System Administrators
Classifier: License :: OSI Approved :: Python Software Foundation License
Classifier: Operating System :: OS Independent
Classifier: Programming Language :: Python
Classifier: Programming Language :: Python :: 2.7
Classifier: Programming Language :: Python :: 3.4
Classifier: Topic :: Software Development :: Libraries :: Python Modules
Classifier: Topic :: Database
Requires-Dist: enum34
Requires-Dist: izihawa-commons (>=0.0.10)
Requires-Dist: pytz
Requires-Dist: requests
Requires-Dist: setuptools
Requires-Dist: six
